chappyner/args.py
chappyner/chappyner_logo.png
chappyner/default_clusters.yml.j2
chappyner/engines.py
chappyner/jobs.py
chappyner/main.py
chappyner/prompts.py
chappyner/utils.py
chappyner-0.3.1.dist-info/licenses/LICENSE
chappyner-0.3.1.dist-info/METADATA
chappyner-0.3.1.dist-info/WHEEL
chappyner-0.3.1.dist-info/entry_points.txt
chappyner-0.3.1.dist-info/top_level.txt
chappyner-0.3.1.dist-info/RECORD
