Metadata-Version: 2.4
Name: chappyner
Version: 0.3.1
Summary: Chappyner
Author-email: Fabio Pitari <f.pitari@cineca.it>, Lucia Rodriguez Muñoz <l.rodriguezmunoz@cineca.it>, Antonio Memmolo <a.memmolo@cineca.it>
Maintainer-email: Fabio Pitari <f.pitari@cineca.it>, Lucia Rodriguez Muñoz <l.rodriguezmunoz@cineca.it>, Antonio Memmolo <a.memmolo@cineca.it>
License:                     GNU GENERAL PUBLIC LICENSE
Classifier: License :: OSI Approved :: GNU General Public License v3 (GPLv3)
Requires-Python: >=3.8
License-File: LICENSE
Requires-Dist: PyYAML
Requires-Dist: jinja2
Requires-Dist: rich
Requires-Dist: notify-py
Requires-Dist: paramiko
Requires-Dist: fabric
Requires-Dist: sshtunnel
Requires-Dist: InquirerPy
Requires-Dist: importlib_resources; python_version < "3.10"
Dynamic: license-file
